{
    "title": "java文档库",
    "author": "lxdreams",
    "description": "jsliang 的文档库. 里面包含了个人撰写的所有前端文章，例如 Vue、React,、ECharts、微信小程序等……",
    "language": "zh-hans",
    "styles": {
        "website": "./static/css/gitbook-configure.css"
    },
    "plugins": [
        "theme-comscore",
        "prism",
        "-highlight",
        "search-pro",
        "-search",
        "-lunr",
        "chapter-fold",
        "splitter",
        "-sharing",
        "donate",
        "tbfed-pagefooter",
        "baidu-tongji",
        "lightbox",
        "advanced-emoji",
        "theme-beauty"
    ],
    "variables": {
        "themeBeauty":{
            "nav":[
                {
                    "url":"https://github.com/lxdreams/java-book",
                    "target":"_blank",
                    "name": "github"
                }
            ]
        }
    },
    "pluginsConfig": {
        "theme-beauty": {
            "search-placeholder":"输入关键字搜索",
            "logo":"static/img/logo.png",
            "favicon": "static/favicon.ico"
        },
        "donate": {
            "button": "打赏",
            "alipayText": "支付宝打赏",
            "wechatText": "微信打赏",
            "alipay": "https://www.deyangwushu.cn/static/blog/images/alipayimg.jpg",
            "wechat": "https://www.deyangwushu.cn/static/blog/images/alipayimg.jpg"
        },
        "prism": {
            "css": [
                "prismjs/themes/prism.css"
            ],
            "lang": {
                "shell": "bash"
            }
        },
        "tbfed-pagefooter": {
            "copyright": "Copyright &copy jsliang.top 2019",
            "modify_label": "该文件修订时间：",
            "modify_format": "YYYY-MM-DD HH:mm:ss"
        },
        "baidu-tongji": {
            "token": "55e7dfe47f4dc1c018d4042fdfa62565"
        }
    }
}